AUTHORS.rst
CONTRIBUTING.rst
HISTORY.rst
LICENSE
MANIFEST.in
README.rst
setup.cfg
setup.py
graphql_ws_django/__init__.py
graphql_ws_django/aiohttp.py
graphql_ws_django/base.py
graphql_ws_django/constants.py
graphql_ws_django/django_channels.py
graphql_ws_django/gevent.py
graphql_ws_django/observable_aiter.py
graphql_ws_django/websockets_lib.py
graphql_ws_django.egg-info/PKG-INFO
graphql_ws_django.egg-info/SOURCES.txt
graphql_ws_django.egg-info/dependency_links.txt
graphql_ws_django.egg-info/not-zip-safe
graphql_ws_django.egg-info/requires.txt
graphql_ws_django.egg-info/top_level.txt
graphql_ws_django/django/__init__.py
graphql_ws_django/django/apps.py
graphql_ws_django/django/consumers.py
graphql_ws_django/django/routing.py
graphql_ws_django/django/subscriptions.py
graphql_ws_django/django/templates/graphene/graphiql.html
tests/__init__.py
tests/test_graphql_ws.py