Metadata-Version: 1.1
Name: graphql-ws-django
Version: 0.3.4
Summary: Websocket server for GraphQL subscriptions
Home-page: https://github.com/Manviel/graphql-ws-django
Author: Syrus Akbary
Author-email: me@syrusakbary.com
License: MIT license
Keywords: graphql,subscriptions,graphene,websockets
Platform: UNKNOWN
Classifier: Development Status :: 2 - Pre-Alpha
Classifier: Intended Audience :: Developers
Classifier: License :: OSI Approved :: MIT License
Classifier: Natural Language :: English
Classifier: Programming Language :: Python :: 2
Classifier: Programming Language :: Python :: 2.6
Classifier: Programming Language :: Python :: 2.7
Classifier: Programming Language :: Python :: 3
Classifier: Programming Language :: Python :: 3.3
Classifier: Programming Language :: Python :: 3.4
Classifier: Programming Language :: Python :: 3.5
